phreeqpy/__init__.py
phreeqpy/_version.py
phreeqpy/input/__init__.py
phreeqpy/input/base.py
phreeqpy/input/datatypes.py
phreeqpy/input/namespace.py
phreeqpy/input/keywords/__init__.py
phreeqpy/input/keywords/advection.py
phreeqpy/input/keywords/calculate_values.py
phreeqpy/input/keywords/copy.py
phreeqpy/input/keywords/database.py
phreeqpy/input/keywords/delete.py
phreeqpy/input/keywords/dump.py
phreeqpy/input/keywords/end.py
phreeqpy/input/keywords/equilibrium_phases.py
phreeqpy/input/keywords/exchange.py
phreeqpy/input/keywords/exchange_master_species.py
phreeqpy/input/keywords/exchange_species.py
phreeqpy/input/keywords/gas_phase.py
phreeqpy/iphreeqc/IPhreeqc.dll
phreeqpy/iphreeqc/__init__.py
phreeqpy/iphreeqc/iphreeqc.py
phreeqpy/iphreeqc/libiphreeqc.0.dylib
phreeqpy/iphreeqc/libiphreeqc.so.0.0.0
phreeqpy/iphreeqc/phreeqc_com.py
phreeqpy/iphreeqc/phreeqc_dll.py
phreeqpy/iphreeqc/phreeqc3/IPhreeqc-3.7.3.dll
phreeqpy/iphreeqc/phreeqc3/libiphreeqc-3.7.1.dylib
phreeqpy/iphreeqc/phreeqc3/libiphreeqc-3.7.3-m1.dylib
phreeqpy/iphreeqc/phreeqc3/libiphreeqc-3.7.3.dylib
phreeqpy/iphreeqc/phreeqc3/libiphreeqc-3.7.3.so
phreeqpy/iphreeqc/phreeqc3/linux_arm_libiphreeqc-3.7.3.so
phreeqpy/phreeqcrm/__init__.py
phreeqpy/phreeqcrm/rm_model.py
phreeqpy-0.6.0.dist-info/AUTHORS
phreeqpy-0.6.0.dist-info/LICENSE
phreeqpy-0.6.0.dist-info/METADATA
phreeqpy-0.6.0.dist-info/WHEEL
phreeqpy-0.6.0.dist-info/top_level.txt
phreeqpy-0.6.0.dist-info/RECORD
