Metadata-Version: 2.1
Name: phreeqpy
Version: 0.6.0
Summary: Python tools for PHREEQC.
Author-email: Mike Müller <mmueller@hydrocomputing.com>
License: BSD-3-Clause
Project-URL: home-page, https://www.phreeqpy.com/
Keywords: PHREEQC,hydrogeochemistry,modeling,modeling coupling
Classifier: Development Status :: 5 - Production/Stable
Classifier: License :: OSI Approved :: BSD License
Classifier: Programming Language :: Python :: 3
Classifier: Environment :: Console
Classifier: Framework :: Jupyter :: JupyterLab
Classifier: Intended Audience :: Developers
Classifier: Intended Audience :: Science/Research
Classifier: Operating System :: Microsoft :: Windows
Classifier: Operating System :: POSIX
Classifier: Operating System :: MacOS :: MacOS X
Classifier: Programming Language :: Python :: Implementation :: CPython
Classifier: Intended Audience :: Science/Research
Classifier: Topic :: Scientific/Engineering :: Hydrology
Requires-Python: >=3.9
License-File: LICENSE
License-File: AUTHORS
Requires-Dist: pywin32 ; os_name == "nt"
